README.md
setup.cfg
setup.py
smsc/__init__.py
smsc/exceptions.py
smsc/smsc.py
smsc/utils.py
smsc/validations.py
smsc_python.egg-info/PKG-INFO
smsc_python.egg-info/SOURCES.txt
smsc_python.egg-info/dependency_links.txt
smsc_python.egg-info/requires.txt
smsc_python.egg-info/top_level.txt