Metadata-Version: 1.1
Name: smsc-python
Version: 1.0.2
Summary: Send SMS with https://www.smsc.com.ar/
Home-page: https://github.com/joaquinmoine/smsc-python
Author: Joaquin Moine
Author-email: joaquinmoine@gmail.com
License: MIT
Keywords: sms,send
Platform: UNKNOWN
Classifier: Development Status :: 5 - Production/Stable
Classifier: Intended Audience :: Developers
Classifier: Intended Audience :: Information Technology
Classifier: Programming Language :: Python :: 3
Classifier: Programming Language :: Python :: 3.2
Classifier: Programming Language :: Python :: 3.3
Classifier: Programming Language :: Python :: 3.4
Classifier: Programming Language :: Python :: 3.5
Classifier: Topic :: Utilities
Classifier: License :: OSI Approved :: MIT License
